Metadata-Version: 1.0
Name: trstringerpypitest
Version: 0.1.4
Summary: Testing and showing demo and sample
Home-page: https://github.com/tstringer/pypitestpkg
Author: Thomas Stringer
Author-email: me@trstringer.com
License: UNKNOWN
Keywords: testing
Platform: UNKNOWN
